ptick_ptock/__init__.py
ptick_ptock/mainfile.py
ptick_ptock/ptick_ptock.py
ptick_ptock-1.0.1.dist-info/LICENSE
ptick_ptock-1.0.1.dist-info/METADATA
ptick_ptock-1.0.1.dist-info/WHEEL
ptick_ptock-1.0.1.dist-info/top_level.txt
ptick_ptock-1.0.1.dist-info/RECORD
