Metadata-Version: 2.1
Name: ptick-ptock
Version: 1.0.1
Summary: tick tock for python
Home-page: https://github.com/ADorigi/ptick-ptock
Author: ADorigi
Author-email: gulegulzaradnan@gmail.com
License: UNKNOWN
Platform: UNKNOWN
Classifier: Programming Language :: Python :: 3
Classifier: License :: OSI Approved :: MIT License
Classifier: Operating System :: OS Independent
Requires-Python: >=3.8
License-File: LICENSE
